sorcerer_forecasts/__init__.py
sorcerer_forecasts/py.typed
sorcerer_forecasts/entity/forecast.py
sorcerer_forecasts/entity/geo.py
sorcerer_forecasts/services/forecast_service.py
sorcerer_forecasts/sources/__init__.py
sorcerer_forecasts/sources/base.py
sorcerer_forecasts/sources/stratocast.py
sorcerer_forecasts/utils/region.py
sorcerer_forecasts-0.1.4.dist-info/METADATA
sorcerer_forecasts-0.1.4.dist-info/WHEEL
sorcerer_forecasts-0.1.4.dist-info/RECORD
