Metadata-Version: 2.4
Name: sorcerer-forecasts
Version: 0.1.4
Summary: Add your description here
Author-email: Alessandro Vecchi <avecchi.53@gmail.com>
Requires-Python: >=3.12
Requires-Dist: h5netcdf>=1.6.4
Requires-Dist: pyjwt>=2.10.1
Requires-Dist: python-dotenv>=1.1.1
Requires-Dist: s3fs>=2024.6.0
Requires-Dist: xarray>=2025.9.0
